colocal/__init__.py
colocal/setup_env.py
colocal-2025.11.6.1340.dist-info/METADATA
colocal-2025.11.6.1340.dist-info/WHEEL
colocal-2025.11.6.1340.dist-info/top_level.txt
colocal-2025.11.6.1340.dist-info/RECORD
