Metadata-Version: 2.4
Name: colocal
Version: 2025.11.6.1340
Summary: Harmonises Jupyter and Colab notebook environments for consistent paths, imports, and working directories
Home-page: https://github.com/project-ida/colocal
Author: project-ida
License: MIT
Requires-Python: >=3.8
Requires-Dist: ipynbname
Dynamic: author
Dynamic: description
Dynamic: description-content-type
Dynamic: home-page
Dynamic: license
Dynamic: requires-dist
Dynamic: requires-python
Dynamic: summary
